<?xml version="1.0"?>
<!DOCTYPE hibernate-mapping PUBLIC "-//Hibernate/Hibernate Mapping DTD 3.0//EN"
"http://hibernate.sourceforge.net/hibernate-mapping-3.0.dtd">
<!-- Generated Dec 13, 2012 3:37:46 PM by Hibernate Tools 3.4.0.CR1 -->
<hibernate-mapping>
    <class name="com.vendhaq.models.VtigerContactroyality" table="vtiger_contactroyality">
        <id name="royalityid" type="int">
            <column name="royalityid" />
            <generator class="assigned" />
        </id>
        <property name="contactid" type="int">
            <column name="contactid" not-null="true" />
        </property>
        <property name="royalitynumber" type="string">
            <column name="royalitynumber" length="100" not-null="true" />
        </property>
        <property name="royalitycount" type="int">
            <column name="royalitycount" not-null="true" />
        </property>
    </class>
</hibernate-mapping>
